Workbook

Sheet Cómo usar
A1: Inventario final Nº1 — Hermanas Caradonti
A2: Armado el | B2: 1 de octubre de 2026, con el recorrido físico del local
A6: Qué NO es | B6: No es el inventario completo del local. Faltan 624 items sin revisar, casi todos sin etiqueta: eso lo tiene que hacer la dependienta.
A8: LAS HOJAS
A9: Inventario final
A10: Qué falta por campo
A11: Completar por proveedor
A12: Sin categoría
A13: Altas resueltas
A14: Backlog | B14: 5 objetos que el inventario declaraba y no estaban en el local.
A15: A confirmar | B15: Dudas concretas que necesitan una respuesta humana antes de publicar.
A17: CÓMO SE LLENA
A18: Celdas amarillas | B18: Son las editables. El resto sale del recorrido o del catálogo: no tocarlas acá.
A19: Orden sugerido | B19: 1) Peso por proveedor 2) Categorías de los 25 3) Lead time por proveedor 4) Stock real 5) Fotos 6) Descripciones
A20: Regla de publicación | B20: Un producto se publica cuando está al 100%. La columna "Listo para publicar" lo calcula sola.
A21: Precio | B21: Ya normalizado a pesos con IVA. Los dólares están convertidos a $1.535. El TC vive en la hoja de precios, no acá.

Sheet Inventario final
A1: Inventario final Nº1 — 149 objetos verificados en el local
A2: Columnas amarillas: para completar. Las demás salen del recorrido o del catálogo maestro.
A4: SKU | B4: Nombre | C4: Categoría | D4: Proveedor | E4: Régimen | F4: Código proveedor | G4: Precio final (ARS c/IVA) | H4: Costo (ARS) | I4: Margen % | J4: Stock real contado | K4: Stock declarado (viejo) | L4: Alto cm | M4: Ancho cm | N4: Prof cm | O4: Peso kg | P4: Lead time días | Q4: Reponible | R4: Materiales | S4: Descripción de venta | T4: Archivo de foto | U4: Identificador URL | V4: Ubicación en el local | W4: Zona | X4: Completitud | Y4: Listo para publicar | Z4: Origen | AA4: Nota del recorrido
A5: HC-BAN-001 | B5: Azucarera Salta alpaca metal & cuero chivo #1 - Cremera Salta alpaca metal & cuero chivo #1 - Bandeja Salta rect alpaca metal & cuero chivo #1 | C5: Bandejas | D5: HC AIRES DEL SUR | E5: Disponible | F5: HC/ADS48 | G5: 880000 | H5: 616000 | I5: =IFERROR((G5-H5)/G5,"") -> 0.3 | K5: 1 | U5: azucarera-salta-alpaca-metal-cuero-chivo-1-cremera-salta-alpaca-metal- | V5: Deposito | W5: Depósito | X5: =IFERROR(COUNTA(C5,G5,J5,L5,O5,P5,R5,S5,T5,U5)/10,"") -> 0.3 | Y5: =IF(AND(C5<>"",G5<>"",J5<>"",O5<>"",S5<>"",T5<>""),"SÍ","no") -> no | Z5: recorrido · marcado ESTÁ
A6: HC-BAN-002 | B6: BANDEJA DECO LODHI VASSA 25,5X19X2 CM | C6: Bandejas | D6: HC MISHKA | E6: Disponible | F6: [FAD08TR2614] | G6: 66463 | H6: 22511 | I6: =IFERROR((G6-H6)/G6,"") -> 0.66130027 | J6: 2 | K6: 0 | L6: 2 | M6: 26 | N6: 19 | U6: bandeja-deco-lodhi-vassa-25-5x19x2-cm | W6: Sin ubicación declarada | X6: =IFERROR(COUNTA(C6,G6,J6,L6,O6,P6,R6,S6,T6,U6)/10,"") -> 0.5 | Y6: =IF(AND(C6<>"",G6<>"",J6<>"",O6<>"",S6<>"",T6<>""),"SÍ","no") -> no | Z6: recorrido · marcado ESTÁ | AA6: revusar precio
A7: HC-BAN-003 | B7: Bandeja Chalten Pirex rect. pino y alpaca #1 | C7: Bandejas | D7: HC AIRES DEL SUR | E7: Disponible | F7: HC/ADS16 | G7: 275000 | H7: 192500 | I7: =IFERROR((G7-H7)/G7,"") -> 0.3 | J7: 1 | K7: 1 | U7: bandeja-chalten-pirex-rect-pino-y-alpaca-1 | V7: showroom | W7: Showroom | X7: =IFERROR(COUNTA(C7,G7,J7,L7,O7,P7,R7,S7,T7,U7)/10,"") -> 0.4 | Y7: =IF(AND(C7<>"",G7<>"",J7<>"",O7<>"",S7<>"",T7<>""),"SÍ","no") -> no | Z7: recorrido · marcado ESTÁ
A8: HC-BAN-004 | B8: Bandeja Chalten Pirex rect. pino y alpaca #3 | C8: Bandejas | D8: HC AIRES DEL SUR | E8: Disponible | F8: HC/ADS18 | G8: 335000 | H8: 234500 | I8: =IFERROR((G8-H8)/G8,"") -> 0.3 | J8: 2 | K8: 2 | U8: bandeja-chalten-pirex-rect-pino-y-alpaca-3 | V8: 1 showroom, 1 placard fondo | W8: Showroom + placard | X8: =IFERROR(COUNTA(C8,G8,J8,L8,O8,P8,R8,S8,T8,U8)/10,"") -> 0.4 | Y8: =IF(AND(C8<>"",G8<>"",J8<>"",O8<>"",S8<>"",T8<>""),"SÍ","no") -> no | Z8: recorrido · marcado ESTÁ
A9: HC-BAN-005 | B9: Bandeja Glaciar Bar, alpaca y onyx blanco #2 | C9: Bandejas | D9: HC AIRES DEL SUR | E9: Disponible | F9: HC/ADS19 | G9: 1480000 | H9: 1036000 | I9: =IFERROR((G9-H9)/G9,"") -> 0.3 | J9: 1 | K9: 1 | U9: bandeja-glaciar-bar-alpaca-y-onyx-blanco-2 | V9: deposito arriba | W9: Depósito | X9: =IFERROR(COUNTA(C9,G9,J9,L9,O9,P9,R9,S9,T9,U9)/10,"") -> 0.4 | Y9: =IF(AND(C9<>"",G9<>"",J9<>"",O9<>"",S9<>"",T9<>""),"SÍ","no") -> no | Z9: recorrido · marcado ESTÁ
A10: HC-BAN-006 | B10: Bandeja doble blanca jose luis | C10: Bandejas | D10: OROPEL | E10: Disponible (consignación) | F10: HC/JLC07 | G10: 666120 | H10: 382200 | I10: =IFERROR((G10-H10)/G10,"") -> 0.42622951 | U10: bandeja-doble-blanca-jose-luis | W10: Sin ubicación declarada | X10: =IFERROR(COUNTA(C10,G10,J10,L10,O10,P10,R10,S10,T10,U10)/10,"") -> 0.3 | Y10: =IF(AND(C10<>"",G10<>"",J10<>"",O10<>"",S10<>"",T10<>""),"SÍ","no") -> no | Z10: recorrido · marcado ESTÁ
A11: HC-BAN-007 | B11: Bandeja metalica 73x19 con manijas bordo | C11: Bandejas | D11: HC HUS COMPRADO | E11: Disponible | F11: HC/HUS-COM24 | G11: 165000 | H11: 115500 | I11: =IFERROR((G11-H11)/G11,"") -> 0.3 | K11: 1 bordo | L11: 19 | M11: 73 | U11: bandeja-metalica-73x19-con-manijas-bordo | V11: showroom | W11: Showroom | X11: =IFERROR(COUNTA(C11,G11,J11,L11,O11,P11,R11,S11,T11,U11)/10,"") -> 0.4 | Y11: =IF(AND(C11<>"",G11<>"",J11<>"",O11<>"",S11<>"",T11<>""),"SÍ","no") -> no | Z11: recorrido · marcado ESTÁ
A12: HC-BAN-008 | B12: Bandeja onix negra | C12: Bandejas | D12: HC AIRES DEL SUR | E12: Disponible | F12: HC/ADS04 | G12: 354900 | H12: 273000 | I12: =IFERROR((G12-H12)/G12,"") -> 0.23076923 | K12: 1 HC COMPRADO | U12: bandeja-onix-negra | V12: showroom | W12: Showroom | X12: =IFERROR(COUNTA(C12,G12,J12,L12,O12,P12,R12,S12,T12,U12)/10,"") -> 0.3 | Y12: =IF(AND(C12<>"",G12<>"",J12<>"",O12<>"",S12<>"",T12<>""),"SÍ","no") -> no | Z12: recorrido · marcado ESTÁ
A13: HC-CAN-001 | B13: CANASTA ABAKO MEDIANO - 28 x H28cm | C13: Canastos y cestería | D13: HC DUKAAN | E13: Disponible | F13: [AAA01MU5589] | G13: 218483 | H13: 74002 | I13: =IFERROR((G13-H13)/G13,"") -> 0.66129173 | K13: 0 | L13: 28 | M13: 28 | U13: canasta-abako-mediano-28-x-h28cm | W13: Sin ubicación declarada | X13: =IFERROR(COUNTA(C13,G13,J13,L13,O13,P13,R13,S13,T13,U13)/10,"") -> 0.4 | Y13: =IF(AND(C13<>"",G13<>"",J13<>"",O13<>"",S13<>"",T13<>""),"SÍ","no") -> no | Z13: recorrido · marcado ESTÁ
A14: HC-CAN-002 | B14: CANASTO GRAZALEMA SET X3 | C14: Canastos y cestería | D14: HC DUKAAN | E14: Disponible | F14: [AAA01MU5457] | G14: 444205 | H14: 150456 | I14: =IFERROR((G14-H14)/G14,"") -> 0.66129152 | K14: 0 | U14: canasto-grazalema-set-x3 | W14: Sin ubicación declarada | X14: =IFERROR(COUNTA(C14,G14,J14,L14,O14,P14,R14,S14,T14,U14)/10,"") -> 0.3 | Y14: =IF(AND(C14<>"",G14<>"",J14<>"",O14<>"",S14<>"",T14<>""),"SÍ","no") -> no | Z14: recorrido · marcado ESTÁ
A15: HC-CAN-003 | B15: CANASTO LIANA CHICO | C15: Canastos y cestería | D15: HC SOFI SUAYA | E15: Disponible | F15: HC/CLA1 | G15: 88572 | H15: 30000 | I15: =IFERROR((G15-H15)/G15,"") -> 0.66129251 | K15: 2 | U15: canasto-liana-chico | V15: Showroom | W15: Showroom | X15: =IFERROR(COUNTA(C15,G15,J15,L15,O15,P15,R15,S15,T15,U15)/10,"") -> 0.3 | Y15: =IF(AND(C15<>"",G15<>"",J15<>"",O15<>"",S15<>"",T15<>""),"SÍ","no") -> no | Z15: recorrido · marcado ESTÁ | AA15: con asas y pintado 1 - 4 sin asa y naturales (distinguir) 2- natural chico con asa
A16: HC-DEC-001 | B16: CUADRO PEDRAGLIO 1 | C16: Objetos y deco | D16: HC JESUS NUDOS | E16: Disponible | F16: HC/Obra2 | G16: 600 | H16: 300 | I16: =IFERROR((G16-H16)/G16,"") -> 0.5 | K16: 1 | U16: cuadro-pedraglio-1 | V16: placard fondo caja | W16: Placard fondo | X16: =IFERROR(COUNTA(C16,G16,J16,L16,O16,P16,R16,S16,T16,U16)/10,"") -> 0.3 | Y16: =IF(AND(C16<>"",G16<>"",J16<>"",O16<>"",S16<>"",T16<>""),"SÍ","no") -> no | Z16: recorrido · marcado ESTÁ
A17: HC-DEC-002 | B17: CUADRO PEDRAGLIO 2 | C17: Objetos y deco | D17: HC JESUS NUDOS | E17: Disponible | F17: HC/Obra3 | G17: 600 | H17: 300 | I17: =IFERROR((G17-H17)/G17,"") -> 0.5 | K17: 1 | U17: cuadro-pedraglio-2 | V17: placard fondo caja | W17: Placard fondo | X17: =IFERROR(COUNTA(C17,G17,J17,L17,O17,P17,R17,S17,T17,U17)/10,"") -> 0.3 | Y17: =IF(AND(C17<>"",G17<>"",J17<>"",O17<>"",S17<>"",T17<>""),"SÍ","no") -> no | Z17: recorrido · marcado ESTÁ
A18: HC-DEC-003 | B18: Cuadro chico DANGER | C18: Objetos y deco | D18: LILA HUME (ISA) | E18: Disponible (consignación) | F18: HC/LHD | G18: 340 | H18: 238 | I18: =IFERROR((G18-H18)/G18,"") -> 0.3 | K18: 1 | U18: cuadro-chico-danger | V18: showroom | W18: Showroom | X18: =IFERROR(COUNTA(C18,G18,J18,L18,O18,P18,R18,S18,T18,U18)/10,"") -> 0.3 | Y18: =IF(AND(C18<>"",G18<>"",J18<>"",O18<>"",S18<>"",T18<>""),"SÍ","no") -> no | Z18: recorrido · marcado ESTÁ
A19: HC-DEC-004 | B19: Cuadro grande EXIT | C19: Objetos y deco | D19: LILA HUME (ISA) | E19: Disponible (consignación) | F19: HC/LHEX | G19: 480 | H19: 336 | I19: =IFERROR((G19-H19)/G19,"") -> 0.3 | K19: 1 | U19: cuadro-grande-exit | V19: showroom | W19: Showroom | X19: =IFERROR(COUNTA(C19,G19,J19,L19,O19,P19,R19,S19,T19,U19)/10,"") -> 0.3 | Y19: =IF(AND(C19<>"",G19<>"",J19<>"",O19<>"",S19<>"",T19<>""),"SÍ","no") -> no | Z19: recorrido · marcado ESTÁ
A20: HC-DEC-005 | B20: Cuadros Chicos 35x45 | C20: Objetos y deco | D20: SANTIAGO CARRERA | E20: Disponible | F20: HC/SANTIC02 | G20: 3070000 | H20: 2302500 | I20: =IFERROR((G20-H20)/G20,"") -> 0.25 | K20: 2 | L20: 45 | M20: 35 | U20: cuadros-chicos-35x45 | V20: Showroom | W20: Showroom | X20: =IFERROR(COUNTA(C20,G20,J20,L20,O20,P20,R20,S20,T20,U20)/10,"") -> 0.4 | Y20: =IF(AND(C20<>"",G20<>"",J20<>"",O20<>"",S20<>"",T20<>""),"SÍ","no") -> no | Z20: recorrido · alta resuelta contra el catálogo | AA20: visto como "Cuadro 1 - Santiago del Campo" · USD 2000 x 1535 = 3.070.000, exacto. El proveedor es SANTIAGO CARRERA, no DEL CAMPO · visto en el local como "Cuadro 2 - Santiago del Campo"
A21: HC-DEC-006 | B21: Espejo Mármol Crema/ Carrara D70 | C21: Objetos y deco | D21: LIMO MARMOL | E21: Disponible (consignación) | F21: HC/LIMO03 | G21: 550 | H21: 440 | I21: =IFERROR((G21-H21)/G21,"") -> 0.2 | K21: 1 | U21: espejo-marmol-crema-carrara-d70 | V21: Showroom | W21: Showroom | X21: =IFERROR(COUNTA(C21,G21,J21,L21,O21,P21,R21,S21,T21,U21)/10,"") -> 0.3 | Y21: =IF(AND(C21<>"",G21<>"",J21<>"",O21<>"",S21<>"",T21<>""),"SÍ","no") -> no | Z21: recorrido · marcado ESTÁ
A22: HC-FLO-001 | B22: Florero Glaciar, alpaca y onyx blanco #1 | C22: Floreros y jarrones | D22: HC AIRES DEL SUR | E22: Disponible | F22: HC/ADS27 | G22: 830000 | H22: 581000 | I22: =IFERROR((G22-H22)/G22,"") -> 0.3 | K22: 1 | U22: florero-glaciar-alpaca-y-onyx-blanco-1 | V22: Deposito estanteria | W22: Depósito | X22: =IFERROR(COUNTA(C22,G22,J22,L22,O22,P22,R22,S22,T22,U22)/10,"") -> 0.3 | Y22: =IF(AND(C22<>"",G22<>"",J22<>"",O22<>"",S22<>"",T22<>""),"SÍ","no") -> no | Z22: recorrido · marcado ESTÁ
A23: HC-FLO-002 | B23: Florero Salta Mini Rectangular Onix Blanco #1 | C23: Floreros y jarrones | D23: HC AIRES DEL SUR | E23: Disponible | F23: HC/ADS63 | G23: 310000 | H23: 217000 | I23: =IFERROR((G23-H23)/G23,"") -> 0.3 | U23: florero-salta-mini-rectangular-onix-blanco-1 | W23: Sin ubicación declarada | X23: =IFERROR(COUNTA(C23,G23,J23,L23,O23,P23,R23,S23,T23,U23)/10,"") -> 0.3 | Y23: =IF(AND(C23<>"",G23<>"",J23<>"",O23<>"",S23<>"",T23<>""),"SÍ","no") -> no | Z23: recorrido · marcado ESTÁ
A24: HC-FLO-003 | B24: Florero Salta Mini Rectangular Onix Blanco #2 | C24: Floreros y jarrones | D24: HC AIRES DEL SUR | E24: Disponible | F24: HC/ADS64 | G24: 450000 | H24: 315000 | I24: =IFERROR((G24-H24)/G24,"") -> 0.3 | U24: florero-salta-mini-rectangular-onix-blanco-2 | W24: Sin ubicación declarada | X24: =IFERROR(COUNTA(C24,G24,J24,L24,O24,P24,R24,S24,T24,U24)/10,"") -> 0.3 | Y24: =IF(AND(C24<>"",G24<>"",J24<>"",O24<>"",S24<>"",T24<>""),"SÍ","no") -> no | Z24: recorrido · marcado ESTÁ
A25: HC-FLO-004 | B25: Florero Shiva, alpaca y onyx blanco #1 (5x4x10) | C25: Floreros y jarrones | D25: HC AIRES DEL SUR | E25: Disponible | F25: HC/ADS49 | G25: 396000 | H25: 316800 | I25: =IFERROR((G25-H25)/G25,"") -> 0.2 | J25: 27 | K25: 0 | L25: 10 | M25: 5 | N25: 4 | U25: florero-shiva-alpaca-y-onyx-blanco-1-5x4x10 | W25: Sin ubicación declarada | X25: =IFERROR(COUNTA(C25,G25,J25,L25,O25,P25,R25,S25,T25,U25)/10,"") -> 0.5 | Y25: =IF(AND(C25<>"",G25<>"",J25<>"",O25<>"",S25<>"",T25<>""),"SÍ","no") -> no | Z25: recorrido · marcado ESTÁ | AA25: uno blanco uno rosa
A26: HC-FLO-005 | B26: Florero Shiva, alpaca y onyx blanco #2 (11.5 x 8.5 x 20) | C26: Floreros y jarrones | D26: HC AIRES DEL SUR | E26: Disponible | F26: HC/ADS50 | G26: 733000 | H26: 586400 | I26: =IFERROR((G26-H26)/G26,"") -> 0.2 | K26: 1 | L26: 20 | M26: 12 | N26: 8 | U26: florero-shiva-alpaca-y-onyx-blanco-2-11-5-x-8-5-x-20 | V26: Showroom | W26: Showroom | X26: =IFERROR(COUNTA(C26,G26,J26,L26,O26,P26,R26,S26,T26,U26)/10,"") -> 0.4 | Y26: =IF(AND(C26<>"",G26<>"",J26<>"",O26<>"",S26<>"",T26<>""),"SÍ","no") -> no | Z26: recorrido · marcado ESTÁ
A27: HC-FLO-006 | B27: Florero grande. | C27: Floreros y jarrones | D27: LIMO MARMOL | E27: Disponible (consignación) | F27: HC/LIMO05 | G27: 350 | H27: 280 | I27: =IFERROR((G27-H27)/G27,"") -> 0.2 | K27: 1 | U27: florero-grande | V27: Showroom | W27: Showroom | X27: =IFERROR(COUNTA(C27,G27,J27,L27,O27,P27,R27,S27,T27,U27)/10,"") -> 0.3 | Y27: =IF(AND(C27<>"",G27<>"",J27<>"",O27<>"",S27<>"",T27<>""),"SÍ","no") -> no | Z27: recorrido · marcado ESTÁ
A28: HC-FLO-007 | B28: JARRON ATENEA VIDRIO · · COLOR GRIS · · MEDIDAS: 31 x H34cm | C28: Floreros y jarrones | D28: HC DUKAAN | E28: Disponible | F28: [FAD08GR6660] | G28: 321082 | H28: 108753 | I28: =IFERROR((G28-H28)/G28,"") -> 0.66129213 | J28: 4 | K28: 4 | L28: 34 | M28: 31 | U28: jarron-atenea-vidrio-color-gris-medidas-31-x-h34cm | V28: 1 Showroom, 1 arriba living, 2 deposito | W28: Showroom | X28: =IFERROR(COUNTA(C28,G28,J28,L28,O28,P28,R28,S28,T28,U28)/10,"") -> 0.5 | Y28: =IF(AND(C28<>"",G28<>"",J28<>"",O28<>"",S28<>"",T28<>""),"SÍ","no") -> no | Z28: recorrido · marcado ESTÁ
A29: HC-GEN-001 | B29: AKAI LARGO | D29: TALLER POSIBLE | E29: Disponible (consignación) | F29: HC/COCO01 | G29: 968968 | H29: 616000 | I29: =IFERROR((G29-H29)/G29,"") -> 0.36427209 | K29: 1 | U29: akai-largo | V29: showroom | W29: Showroom | X29: =IFERROR(COUNTA(C29,G29,J29,L29,O29,P29,R29,S29,T29,U29)/10,"") -> 0.2 | Y29: =IF(AND(C29<>"",G29<>"",J29<>"",O29<>"",S29<>"",T29<>""),"SÍ","no") -> no | Z29: recorrido · marcado ESTÁ
A30: HC-GEN-002 | B30: BACKGAMMON | D30: HC SOFI SUAYA | E30: Disponible | F30: HC/BG | G30: 1328580 | H30: 450000 | I30: =IFERROR((G30-H30)/G30,"") -> 0.66129251 | J30: 2 | K30: 2 | U30: backgammon | V30: Placard fondo 1, 1 Deposito estanteria | W30: Placard fondo | X30: =IFERROR(COUNTA(C30,G30,J30,L30,O30,P30,R30,S30,T30,U30)/10,"") -> 0.3 | Y30: =IF(AND(C30<>"",G30<>"",J30<>"",O30<>"",S30<>"",T30<>""),"SÍ","no") -> no | Z30: recorrido · marcado ESTÁ
A31: HC-GEN-003 | B31: Butaca Umbral | D31: HC | E31: Disponible | F31: HC/BU | G31: 2983105 | H31: 1010400 | I31: =IFERROR((G31-H31)/G31,"") -> 0.66129251 | J31: 1 | K31: 1 | U31: butaca-umbral | V31: showroom | W31: Showroom | X31: =IFERROR(COUNTA(C31,G31,J31,L31,O31,P31,R31,S31,T31,U31)/10,"") -> 0.3 | Y31: =IF(AND(C31<>"",G31<>"",J31<>"",O31<>"",S31<>"",T31<>""),"SÍ","no") -> no | Z31: recorrido · marcado ESTÁ
A32: HC-GEN-004 | B32: CABALLITO | D32: FERMOB | E32: Disponible (consignación) | F32: HC/FBCLL | G32: 650 | H32: 552 | I32: =IFERROR((G32-H32)/G32,"") -> 0.15076923 | K32: 1 | U32: caballito | V32: PATIO | W32: Patio | X32: =IFERROR(COUNTA(C32,G32,J32,L32,O32,P32,R32,S32,T32,U32)/10,"") -> 0.2 | Y32: =IF(AND(C32<>"",G32<>"",J32<>"",O32<>"",S32<>"",T32<>""),"SÍ","no") -> no | Z32: recorrido · marcado ESTÁ
A33: HC-GEN-005 | B33: CENICEROS | D33: HC | E33: Disponible | F33: HC/CEN | G33: 206668 | H33: 70000 | I33: =IFERROR((G33-H33)/G33,"") -> 0.66129251 | K33: 1 BLANCO/ 1 NEGRO | U33: ceniceros | V33: showroom | W33: Showroom | X33: =IFERROR(COUNTA(C33,G33,J33,L33,O33,P33,R33,S33,T33,U33)/10,"") -> 0.2 | Y33: =IF(AND(C33<>"",G33<>"",J33<>"",O33<>"",S33<>"",T33<>""),"SÍ","no") -> no | Z33: recorrido · marcado ESTÁ
A34: HC-GEN-006 | B34: Casitas acrilico - chicas | D34: FABIANA BARREDA | E34: Disponible | F34: HC/FABI02 | G34: 347000 | H34: 242900 | I34: =IFERROR((G34-H34)/G34,"") -> 0.3 | J34: 2 | K34: 2 | U34: casitas-acrilico-chicas | V34: showroom | W34: Showroom | X34: =IFERROR(COUNTA(C34,G34,J34,L34,O34,P34,R34,S34,T34,U34)/10,"") -> 0.3 | Y34: =IF(AND(C34<>"",G34<>"",J34<>"",O34<>"",S34<>"",T34<>""),"SÍ","no") -> no | Z34: recorrido · marcado ESTÁ
A35: HC-GEN-007 | B35: Casitas acrilicos - grandes | D35: FABIANA BARREDA | E35: Disponible | F35: HC/FABI01 | G35: 629200 | H35: 400000 | I35: =IFERROR((G35-H35)/G35,"") -> 0.36427209 | J35: 1 | K35: 1 | U35: casitas-acrilicos-grandes | W35: Sin ubicación declarada | X35: =IFERROR(COUNTA(C35,G35,J35,L35,O35,P35,R35,S35,T35,U35)/10,"") -> 0.3 | Y35: =IF(AND(C35<>"",G35<>"",J35<>"",O35<>"",S35<>"",T35<>""),"SÍ","no") -> no | Z35: recorrido · marcado ESTÁ
A36: HC-GEN-008 | B36: Cilindro largo (78x18diam) | D36: CSALOM ATELIER | E36: Disponible | F36: HC/CSCL | G36: 845000 | H36: 650000 | I36: =IFERROR((G36-H36)/G36,"") -> 0.23076923 | K36: 1 | L36: 18 | M36: 78 | U36: cilindro-largo-78x18diam | V36: Showroom | W36: Showroom | X36: =IFERROR(COUNTA(C36,G36,J36,L36,O36,P36,R36,S36,T36,U36)/10,"") -> 0.3 | Y36: =IF(AND(C36<>"",G36<>"",J36<>"",O36<>"",S36<>"",T36<>""),"SÍ","no") -> no | Z36: recorrido · marcado ESTÁ
A37: HC-GEN-009 | B37: Cilindro mediano (58x18diam) | D37: CSALOM ATELIER | E37: Disponible | F37: HC/CSCM | G37: 715000 | H37: 550000 | I37: =IFERROR((G37-H37)/G37,"") -> 0.23076923 | J37: 1 | K37: 1 | L37: 18 | M37: 58 | U37: cilindro-mediano-58x18diam | V37: Showroom | W37: Showroom | X37: =IFERROR(COUNTA(C37,G37,J37,L37,O37,P37,R37,S37,T37,U37)/10,"") -> 0.4 | Y37: =IF(AND(C37<>"",G37<>"",J37<>"",O37<>"",S37<>"",T37<>""),"SÍ","no") -> no | Z37: recorrido · marcado ESTÁ
A38: HC-GEN-010 | B38: Cojin Yana Camino blanco y negro 30X45 | D38: HC PAIS TEXTIL PERU | E38: Disponible | F38: HC/PT35 | G38: 112 | H38: 58330 | I38: =IFERROR((G38-H38)/G38,"") -> -519.80357 | L38: 45 | M38: 30 | U38: cojin-yana-camino-blanco-y-negro-30x45 | W38: Sin ubicación declarada | X38: =IFERROR(COUNTA(C38,G38,J38,L38,O38,P38,R38,S38,T38,U38)/10,"") -> 0.3 | Y38: =IF(AND(C38<>"",G38<>"",J38<>"",O38<>"",S38<>"",T38<>""),"SÍ","no") -> no | Z38: recorrido · marcado ESTÁ
A39: HC-GEN-011 | B39: Cojin Yana alpaca y algodón con flecos 50X50 | D39: HC PAIS TEXTIL PERU | E39: Disponible | F39: HC/PT36 | G39: 139 | H39: 72145 | I39: =IFERROR((G39-H39)/G39,"") -> -518.02878 | L39: 50 | M39: 50 | U39: cojin-yana-alpaca-y-algodon-con-flecos-50x50 | W39: Sin ubicación declarada | X39: =IFERROR(COUNTA(C39,G39,J39,L39,O39,P39,R39,S39,T39,U39)/10,"") -> 0.3 | Y39: =IF(AND(C39<>"",G39<>"",J39<>"",O39<>"",S39<>"",T39<>""),"SÍ","no") -> no | Z39: recorrido · marcado ESTÁ
A40: HC-GEN-012 | B40: Cojin Yana block blanco y negro 30X45 | D40: HC PAIS TEXTIL PERU | E40: Disponible | F40: HC/PT33 | G40: 112 | H40: 58330 | I40: =IFERROR((G40-H40)/G40,"") -> -519.80357 | L40: 45 | M40: 30 | U40: cojin-yana-block-blanco-y-negro-30x45 | W40: Sin ubicación declarada | X40: =IFERROR(COUNTA(C40,G40,J40,L40,O40,P40,R40,S40,T40,U40)/10,"") -> 0.3 | Y40: =IF(AND(C40<>"",G40<>"",J40<>"",O40<>"",S40<>"",T40<>""),"SÍ","no") -> no | Z40: recorrido · marcado ESTÁ
A41: HC-GEN-013 | B41: Cojin Yana rayas verticales blanco y negro 30X45 | D41: HC PAIS TEXTIL PERU | E41: Disponible | F41: HC/PT34 | G41: 112 | H41: 58330 | I41: =IFERROR((G41-H41)/G41,"") -> -519.80357 | L41: 45 | M41: 30 | U41: cojin-yana-rayas-verticales-blanco-y-negro-30x45 | W41: Sin ubicación declarada | X41: =IFERROR(COUNTA(C41,G41,J41,L41,O41,P41,R41,S41,T41,U41)/10,"") -> 0.3 | Y41: =IF(AND(C41<>"",G41<>"",J41<>"",O41<>"",S41<>"",T41<>""),"SÍ","no") -> no | Z41: recorrido · marcado ESTÁ
A42: HC-GEN-014 | B42: GALLO altura 55cm/ 35x30 | D42: DESIREE CERAMISTA | E42: Disponible (consignación) | F42: HC/CER/GALLO | G42: 900 | H42: 630 | I42: =IFERROR((G42-H42)/G42,"") -> 0.3 | J42: 5 | K42: 1 DE UN CLIENTE | L42: 30 | M42: 35 | U42: gallo-altura-55cm-35x30 | V42: showroom | W42: Showroom | X42: =IFERROR(COUNTA(C42,G42,J42,L42,O42,P42,R42,S42,T42,U42)/10,"") -> 0.4 | Y42: =IF(AND(C42<>"",G42<>"",J42<>"",O42<>"",S42<>"",T42<>""),"SÍ","no") -> no | Z42: recorrido · marcado ESTÁ
A43: HC-GEN-015 | B43: LIBRO CHUBUT | D43: HC | E43: Disponible | F43: HC/CHB | G43: 54900 | H43: 31500 | I43: =IFERROR((G43-H43)/G43,"") -> 0.42622951 | K43: 3 | U43: libro-chubut | V43: 1 showroom, 2 deposito estanteria | W43: Showroom | X43: =IFERROR(COUNTA(C43,G43,J43,L43,O43,P43,R43,S43,T43,U43)/10,"") -> 0.2 | Y43: =IF(AND(C43<>"",G43<>"",J43<>"",O43<>"",S43<>"",T43<>""),"SÍ","no") -> no | Z43: recorrido · marcado ESTÁ
A44: HC-GEN-016 | B44: LOUNGEARMCHAIR LUXEMBOURG | D44: FERMOB | E44: Disponible (consignación) | F44: HC/FBLAL | G44: 990 | H44: 842 | I44: =IFERROR((G44-H44)/G44,"") -> 0.14949495 | J44: 1 | K44: 1 BORDEU | U44: loungearmchair-luxembourg | V44: PATIO | W44: Patio | X44: =IFERROR(COUNTA(C44,G44,J44,L44,O44,P44,R44,S44,T44,U44)/10,"") -> 0.3 | Y44: =IF(AND(C44<>"",G44<>"",J44<>"",O44<>"",S44<>"",T44<>""),"SÍ","no") -> no | Z44: recorrido · marcado ESTÁ
A45: HC-GEN-017 | B45: NUDOS L 45X45 APROX | D45: HC JESUS NUDOS | E45: Disponible | F45: HC/JN03 | G45: 550 | H45: 385 | I45: =IFERROR((G45-H45)/G45,"") -> 0.3 | K45: 1 blanco, negro, azul, naranja | L45: 45 | M45: 45 | U45: nudos-l-45x45-aprox | V45: Showroom | W45: Showroom | X45: =IFERROR(COUNTA(C45,G45,J45,L45,O45,P45,R45,S45,T45,U45)/10,"") -> 0.3 | Y45: =IF(AND(C45<>"",G45<>"",J45<>"",O45<>"",S45<>"",T45<>""),"SÍ","no") -> no | Z45: recorrido · marcado ESTÁ
A46: HC-GEN-018 | B46: PAVO altura 25cm/ 40X40 | D46: DESIREE CERAMISTA | E46: Disponible (consignación) | F46: HC/CER/PAVO | G46: 850 | H46: 595 | I46: =IFERROR((G46-H46)/G46,"") -> 0.3 | K46: 1 | L46: 40 | M46: 40 | U46: pavo-altura-25cm-40x40 | V46: estudio | W46: Estudio | X46: =IFERROR(COUNTA(C46,G46,J46,L46,O46,P46,R46,S46,T46,U46)/10,"") -> 0.3 | Y46: =IF(AND(C46<>"",G46<>"",J46<>"",O46<>"",S46<>"",T46<>""),"SÍ","no") -> no | Z46: recorrido · marcado ESTÁ
A47: HC-GEN-019 | B47: PETACA | D47: HC SOFI SUAYA | E47: Disponible | F47: HC/PH01 | G47: 120 | H47: 84 | I47: =IFERROR((G47-H47)/G47,"") -> 0.3 | J47: 3 | K47: 3 | U47: petaca | V47: 1 showroom, 3 deposito | W47: Showroom | X47: =IFERROR(COUNTA(C47,G47,J47,L47,O47,P47,R47,S47,T47,U47)/10,"") -> 0.3 | Y47: =IF(AND(C47<>"",G47<>"",J47<>"",O47<>"",S47<>"",T47<>""),"SÍ","no") -> no | Z47: recorrido · marcado ESTÁ
A48: HC-GEN-020 | B48: Par Sujeta libros salta - Alpaca y Onix blanco | D48: HC AIRES DEL SUR | E48: Disponible | F48: HC/ADS01 | G48: 850000 | H48: 595000 | I48: =IFERROR((G48-H48)/G48,"") -> 0.3 | K48: 1 | U48: par-sujeta-libros-salta-alpaca-y-onix-blanco | V48: showroom | W48: Showroom | X48: =IFERROR(COUNTA(C48,G48,J48,L48,O48,P48,R48,S48,T48,U48)/10,"") -> 0.2 | Y48: =IF(AND(C48<>"",G48<>"",J48<>"",O48<>"",S48<>"",T48<>""),"SÍ","no") -> no | Z48: recorrido · marcado ESTÁ
A49: HC-GEN-021 | B49: Porta hielo cerro alpaca y cuerno de chivo #1 | D49: HC AIRES DEL SUR | E49: Disponible | F49: HC/ADS32 | G49: 200000 | H49: 140000 | I49: =IFERROR((G49-H49)/G49,"") -> 0.3 | K49: 0 | U49: porta-hielo-cerro-alpaca-y-cuerno-de-chivo-1 | W49: Sin ubicación declarada | X49: =IFERROR(COUNTA(C49,G49,J49,L49,O49,P49,R49,S49,T49,U49)/10,"") -> 0.2 | Y49: =IF(AND(C49<>"",G49<>"",J49<>"",O49<>"",S49<>"",T49<>""),"SÍ","no") -> no | Z49: recorrido · marcado ESTÁ
A50: HC-GEN-022 | B50: RUFFO PELOTA | D50: RUFFO | E50: Disponible (consignación) | F50: HC/RF03 | G50: 1966250 | H50: 1250000 | I50: =IFERROR((G50-H50)/G50,"") -> 0.36427209 | K50: 1 | U50: ruffo-pelota | V50: showroom | W50: Showroom | X50: =IFERROR(COUNTA(C50,G50,J50,L50,O50,P50,R50,S50,T50,U50)/10,"") -> 0.2 | Y50: =IF(AND(C50<>"",G50<>"",J50<>"",O50<>"",S50<>"",T50<>""),"SÍ","no") -> no | Z50: recorrido · alta resuelta contra el catálogo | AA50: visto como "banco pelota" · precio 1.967.000 vs 1.966.250
A51: HC-GEN-023 | B51: Resma cuadrada (58x58x35h) | D51: CSALOM ATELIER | E51: Disponible | F51: HC/CSRG | G51: 910000 | H51: 700000 | I51: =IFERROR((G51-H51)/G51,"") -> 0.23076923 | K51: 1 | L51: 35 | M51: 58 | N51: 58 | U51: resma-cuadrada-58x58x35h | V51: Showroom | W51: Showroom | X51: =IFERROR(COUNTA(C51,G51,J51,L51,O51,P51,R51,S51,T51,U51)/10,"") -> 0.3 | Y51: =IF(AND(C51<>"",G51<>"",J51<>"",O51<>"",S51<>"",T51<>""),"SÍ","no") -> no | Z51: recorrido · marcado ESTÁ
A52: HC-GEN-024 | B52: Romance del vestido. | D52: HC DIAZ ORTIZ | E52: Disponible (consignación) | F52: HC/DO01 | G52: 80000 | H52: 48000 | I52: =IFERROR((G52-H52)/G52,"") -> 0.4 | K52: 1 | U52: romance-del-vestido | V52: tiene hundida la tapa | W52: Otras ubicaciones | X52: =IFERROR(COUNTA(C52,G52,J52,L52,O52,P52,R52,S52,T52,U52)/10,"") -> 0.2 | Y52: =IF(AND(C52<>"",G52<>"",J52<>"",O52<>"",S52<>"",T52<>""),"SÍ","no") -> no | Z52: recorrido · alta resuelta contra el catálogo | AA52: visto como "Libro - El romance vestido - Agustina Bothlink" · "Romance del vestido.", HC DIAZ ORTIZ
A53: HC-GEN-025 | B53: libro Bordeu | D53: HC DIAZ ORTIZ | E53: Disponible (consignación) | F53: HC/AM1 | G53: 100000 | H53: 60000 | I53: =IFERROR((G53-H53)/G53,"") -> 0.4 | J53: 11 | K53: 11 | U53: libro-bordeu | V53: 2 Showroom, 6 placard fondo | W53: Showroom + placard | X53: =IFERROR(COUNTA(C53,G53,J53,L53,O53,P53,R53,S53,T53,U53)/10,"") -> 0.3 | Y53: =IF(AND(C53<>"",G53<>"",J53<>"",O53<>"",S53<>"",T53<>""),"SÍ","no") -> no | Z53: recorrido · marcado ESTÁ
A54: HC-ILU-001 | B54: LAMPARA BALAD 25H | C54: Iluminación | D54: FERMOB | E54: Disponible (consignación) | F54: HC/FBLB | G54: 160 | H54: 136 | I54: =IFERROR((G54-H54)/G54,"") -> 0.15 | K54: 1 CREMA 1 VERDE 1 NEGRA | U54: lampara-balad-25h | V54: PATIO | W54: Patio | X54: =IFERROR(COUNTA(C54,G54,J54,L54,O54,P54,R54,S54,T54,U54)/10,"") -> 0.3 | Y54: =IF(AND(C54<>"",G54<>"",J54<>"",O54<>"",S54<>"",T54<>""),"SÍ","no") -> no | Z54: recorrido · marcado ESTÁ
A55: HC-ILU-002 | B55: LAMPARA BALAD 38H (BAMBOO) | C55: Iluminación | D55: FERMOB | E55: Disponible (consignación) | F55: HC/FBLBB | G55: 300 | H55: 255 | I55: =IFERROR((G55-H55)/G55,"") -> 0.15 | K55: 1 | U55: lampara-balad-38h-bamboo | V55: PATIO | W55: Patio | X55: =IFERROR(COUNTA(C55,G55,J55,L55,O55,P55,R55,S55,T55,U55)/10,"") -> 0.3 | Y55: =IF(AND(C55<>"",G55<>"",J55<>"",O55<>"",S55<>"",T55<>""),"SÍ","no") -> no | Z55: recorrido · marcado ESTÁ
A56: HC-ILU-003 | B56: LAMPARA BALAD SET X3 | C56: Iluminación | D56: FERMOB | E56: Disponible (consignación) | F56: HC/FBLB3 | G56: 335 | H56: 285 | I56: =IFERROR((G56-H56)/G56,"") -> 0.14925373 | K56: 1 VERDE | U56: lampara-balad-set-x3 | V56: PATIO | W56: Patio | X56: =IFERROR(COUNTA(C56,G56,J56,L56,O56,P56,R56,S56,T56,U56)/10,"") -> 0.3 | Y56: =IF(AND(C56<>"",G56<>"",J56<>"",O56<>"",S56<>"",T56<>""),"SÍ","no") -> no | Z56: recorrido · marcado ESTÁ
A57: HC-ILU-004 | B57: LAMPARA DE PIE BALAD OFFSET STAND | C57: Iluminación | D57: FERMOB | E57: Disponible (consignación) | F57: HC/FBLPL | G57: 640 | H57: 544 | I57: =IFERROR((G57-H57)/G57,"") -> 0.15 | K57: 1 | U57: lampara-de-pie-balad-offset-stand | V57: PATIO | W57: Patio | X57: =IFERROR(COUNTA(C57,G57,J57,L57,O57,P57,R57,S57,T57,U57)/10,"") -> 0.3 | Y57: =IF(AND(C57<>"",G57<>"",J57<>"",O57<>"",S57<>"",T57<>""),"SÍ","no") -> no | Z57: recorrido · marcado ESTÁ
A58: HC-ILU-005 | B58: LAMPARA DE PIE BALAD UPRIGHT STAND | C58: Iluminación | D58: FERMOB | E58: Disponible (consignación) | F58: HC/FBLPS | G58: 370 | H58: 314 | I58: =IFERROR((G58-H58)/G58,"") -> 0.15135135 | K58: 1 | U58: lampara-de-pie-balad-upright-stand | V58: PATIO | W58: Patio | X58: =IFERROR(COUNTA(C58,G58,J58,L58,O58,P58,R58,S58,T58,U58)/10,"") -> 0.3 | Y58: =IF(AND(C58<>"",G58<>"",J58<>"",O58<>"",S58<>"",T58<>""),"SÍ","no") -> no | Z58: recorrido · marcado ESTÁ
A59: HC-ILU-006 | B59: Lampara Mesa Led | C59: Iluminación | E59: Disponible | G59: 129000 | I59: =IFERROR((G59-H59)/G59,"") -> 1 | J59: 1 | U59: lampara-mesa-led | X59: =IFERROR(COUNTA(C59,G59,J59,L59,O59,P59,R59,S59,T59,U59)/10,"") -> 0.4 | Y59: =IF(AND(C59<>"",G59<>"",J59<>"",O59<>"",S59<>"",T59<>""),"SÍ","no") -> no | Z59: NUEVO · no estaba en el inventario | AA59: Las dos lámparas LED del catálogo (I294, I295) ya estaban marcadas aparte
A60: HC-ILU-007 | B60: Lampara led hongo bajo | C60: Iluminación | D60: HC | E60: Disponible | F60: HC/LH | G60: 265716 | H60: 90000 | I60: =IFERROR((G60-H60)/G60,"") -> 0.66129251 | K60: 1 negra | U60: lampara-led-hongo-bajo | V60: deposito estanteria | W60: Depósito | X60: =IFERROR(COUNTA(C60,G60,J60,L60,O60,P60,R60,S60,T60,U60)/10,"") -> 0.3 | Y60: =IF(AND(C60<>"",G60<>"",J60<>"",O60<>"",S60<>"",T60<>""),"SÍ","no") -> no | Z60: recorrido · marcado ESTÁ
A61: HC-LIB-001 | B61: Allan McCollum | C61: Libros | D61: HC KBB | E61: Disponible | F61: HC/KBBAMC | G61: 80000 | H61: 52000 | I61: =IFERROR((G61-H61)/G61,"") -> 0.35 | K61: 1 | U61: allan-mccollum | V61: SHOWROOM | W61: Showroom | X61: =IFERROR(COUNTA(C61,G61,J61,L61,O61,P61,R61,S61,T61,U61)/10,"") -> 0.3 | Y61: =IF(AND(C61<>"",G61<>"",J61<>"",O61<>"",S61<>"",T61<>""),"SÍ","no") -> no | Z61: recorrido · marcado ESTÁ
A62: HC-LIB-002 | B62: Art & Language Homes | C62: Libros | D62: HC KBB | E62: Disponible | F62: 978-3-905701-56-2 | G62: 50000 | H62: 32500 | I62: =IFERROR((G62-H62)/G62,"") -> 0.35 | J62: 2 | K62: 2 | U62: art-language-homes | V62: Showroom | W62: Showroom | X62: =IFERROR(COUNTA(C62,G62,J62,L62,O62,P62,R62,S62,T62,U62)/10,"") -> 0.4 | Y62: =IF(AND(C62<>"",G62<>"",J62<>"",O62<>"",S62<>"",T62<>""),"SÍ","no") -> no | Z62: recorrido · marcado ESTÁ
A63: HC-LIB-003 | B63: Arte Urbana | C63: Libros | D63: HC KBB | E63: Disponible | F63: 978-631-90766-0-8 | G63: 95000 | H63: 61750 | I63: =IFERROR((G63-H63)/G63,"") -> 0.35 | J63: 3 | K63: 3 | U63: arte-urbana | V63: showroom/placard | W63: Showroom + placard | X63: =IFERROR(COUNTA(C63,G63,J63,L63,O63,P63,R63,S63,T63,U63)/10,"") -> 0.4 | Y63: =IF(AND(C63<>"",G63<>"",J63<>"",O63<>"",S63<>"",T63<>""),"SÍ","no") -> no | Z63: recorrido · marcado ESTÁ
A64: HC-LIB-004 | B64: COSAS el mundo no existe | C64: Libros | D64: HC KBB | E64: Disponible | F64: 978-987-783-993-7 | G64: 54000 | H64: 35100 | I64: =IFERROR((G64-H64)/G64,"") -> 0.35 | J64: 2 | K64: 2 | U64: cosas-el-mundo-no-existe | V64: 1 showroom/2 placard | W64: Showroom + placard | X64: =IFERROR(COUNTA(C64,G64,J64,L64,O64,P64,R64,S64,T64,U64)/10,"") -> 0.4 | Y64: =IF(AND(C64<>"",G64<>"",J64<>"",O64<>"",S64<>"",T64<>""),"SÍ","no") -> no | Z64: recorrido · marcado ESTÁ
A65: HC-LIB-005 | B65: DOMA_17 | C65: Libros | D65: HC KBB | E65: Disponible | F65: 978-987-45-7832-7 | G65: 56000 | H65: 36400 | I65: =IFERROR((G65-H65)/G65,"") -> 0.35 | J65: 4 | K65: 4 | U65: doma-17 | V65: Showroom/placard fondo | W65: Showroom + placard | X65: =IFERROR(COUNTA(C65,G65,J65,L65,O65,P65,R65,S65,T65,U65)/10,"") -> 0.4 | Y65: =IF(AND(C65<>"",G65<>"",J65<>"",O65<>"",S65<>"",T65<>""),"SÍ","no") -> no | Z65: recorrido · marcado ESTÁ
A66: HC-LIB-006 | B66: El Amor imperfecto | C66: Libros | D66: HC KBB | E66: Disponible | F66: 978-987-45783-5-8 | G66: 45000 | H66: 29250 | I66: =IFERROR((G66-H66)/G66,"") -> 0.35 | J66: 5 | K66: 5 | U66: el-amor-imperfecto | V66: 2 showroom, 3 placard | W66: Showroom + placard | X66: =IFERROR(COUNTA(C66,G66,J66,L66,O66,P66,R66,S66,T66,U66)/10,"") -> 0.4 | Y66: =IF(AND(C66<>"",G66<>"",J66<>"",O66<>"",S66<>"",T66<>""),"SÍ","no") -> no | Z66: recorrido · marcado ESTÁ
A67: HC-LIB-007 | B67: El Asesino de tu Herencia | C67: Libros | D67: HC KBB | E67: Disponible | F67: 978-987-33-0567-2 | G67: 47000 | H67: 30550 | I67: =IFERROR((G67-H67)/G67,"") -> 0.35 | K67: 4 | U67: el-asesino-de-tu-herencia | V67: Showroom/placard fondo | W67: Showroom + placard | X67: =IFERROR(COUNTA(C67,G67,J67,L67,O67,P67,R67,S67,T67,U67)/10,"") -> 0.3 | Y67: =IF(AND(C67<>"",G67<>"",J67<>"",O67<>"",S67<>"",T67<>""),"SÍ","no") -> no | Z67: recorrido · marcado ESTÁ | AA67: precio lista 50000
A68: HC-LIB-008 | B68: Enlarge | C68: Libros | D68: HC KBB | E68: Disponible | F68: 978-987-33-0781-2 | G68: 55000 | H68: 35750 | I68: =IFERROR((G68-H68)/G68,"") -> 0.35 | J68: 4 | K68: 4 | U68: enlarge | V68: Showroom/placard fondo | W68: Showroom + placard | X68: =IFERROR(COUNTA(C68,G68,J68,L68,O68,P68,R68,S68,T68,U68)/10,"") -> 0.4 | Y68: =IF(AND(C68<>"",G68<>"",J68<>"",O68<>"",S68<>"",T68<>""),"SÍ","no") -> no | Z68: recorrido · marcado ESTÁ
A69: HC-LIB-009 | B69: Esto fue otro lugar | C69: Libros | D69: HC KBB | E69: Disponible | F69: 978-987-21256-2-2 | G69: 78000 | H69: 50700 | I69: =IFERROR((G69-H69)/G69,"") -> 0.35 | J69: 4 | K69: 4 | U69: esto-fue-otro-lugar | V69: 3 deposito estanteria, 1 showroom | W69: Showroom | X69: =IFERROR(COUNTA(C69,G69,J69,L69,O69,P69,R69,S69,T69,U69)/10,"") -> 0.4 | Y69: =IF(AND(C69<>"",G69<>"",J69<>"",O69<>"",S69<>"",T69<>""),"SÍ","no") -> no | Z69: recorrido · marcado ESTÁ
A70: HC-LIB-010 | B70: Graciela Hasper | C70: Libros | D70: HC KBB | E70: Disponible | F70: 978-1-73684-083-2 | G70: 63500 | H70: 41275 | I70: =IFERROR((G70-H70)/G70,"") -> 0.35 | J70: 4 | K70: 4 | U70: graciela-hasper | V70: 1 showroom, 3 placard | W70: Showroom + placard | X70: =IFERROR(COUNTA(C70,G70,J70,L70,O70,P70,R70,S70,T70,U70)/10,"") -> 0.4 | Y70: =IF(AND(C70<>"",G70<>"",J70<>"",O70<>"",S70<>"",T70<>""),"SÍ","no") -> no | Z70: recorrido · marcado ESTÁ
A71: HC-LIB-011 | B71: Guillermo Kuitca, Collected Drawings 1971 -2017 | C71: Libros | D71: HC KBB | E71: Disponible | F71: 978-3-03764-513-0 | G71: 153000 | H71: 99450 | I71: =IFERROR((G71-H71)/G71,"") -> 0.35 | J71: 4 | K71: 4 | U71: guillermo-kuitca-collected-drawings-1971-2017 | V71: 1 FOTOS, 3 SHOWROOM | W71: Showroom | X71: =IFERROR(COUNTA(C71,G71,J71,L71,O71,P71,R71,S71,T71,U71)/10,"") -> 0.4 | Y71: =IF(AND(C71<>"",G71<>"",J71<>"",O71<>"",S71<>"",T71<>""),"SÍ","no") -> no | Z71: recorrido · marcado ESTÁ
A72: HC-LIB-012 | B72: Hogar | C72: Libros | D72: HC KBB | E72: Disponible | F72: 978-987-45783-1-0 | G72: 36000 | H72: 23400 | I72: =IFERROR((G72-H72)/G72,"") -> 0.35 | J72: 2 | K72: 3 | U72: hogar | W72: Sin ubicación declarada | X72: =IFERROR(COUNTA(C72,G72,J72,L72,O72,P72,R72,S72,T72,U72)/10,"") -> 0.4 | Y72: =IF(AND(C72<>"",G72<>"",J72<>"",O72<>"",S72<>"",T72<>""),"SÍ","no") -> no | Z72: recorrido · marcado ESTÁ
A73: HC-LIB-013 | B73: Jason Rhoades: The Big Picture | C73: Libros | D73: HC KBB | E73: Disponible | F73: HC/KBBJR | G73: 80000 | H73: 52000 | I73: =IFERROR((G73-H73)/G73,"") -> 0.35 | J73: 1 | K73: 1 | U73: jason-rhoades-the-big-picture | V73: SHOWROOM | W73: Showroom | X73: =IFERROR(COUNTA(C73,G73,J73,L73,O73,P73,R73,S73,T73,U73)/10,"") -> 0.4 | Y73: =IF(AND(C73<>"",G73<>"",J73<>"",O73<>"",S73<>"",T73<>""),"SÍ","no") -> no | Z73: recorrido · marcado ESTÁ
A74: HC-LIB-014 | B74: Joaquin Boz | C74: Libros | D74: HC KBB | E74: Disponible | F74: 978-987-45783-8-9 | G74: 71000 | H74: 46150 | I74: =IFERROR((G74-H74)/G74,"") -> 0.35 | J74: 2 | K74: 2 | U74: joaquin-boz | V74: 1 estudio, 1 showroom | W74: Showroom | X74: =IFERROR(COUNTA(C74,G74,J74,L74,O74,P74,R74,S74,T74,U74)/10,"") -> 0.4 | Y74: =IF(AND(C74<>"",G74<>"",J74<>"",O74<>"",S74<>"",T74<>""),"SÍ","no") -> no | Z74: recorrido · marcado ESTÁ | AA74: precio 74k
A75: HC-LIB-015 | B75: Mappa | C75: Libros | D75: HC KBB | E75: Disponible | F75: HC/KBBMPP | G75: 55000 | H75: 35750 | I75: =IFERROR((G75-H75)/G75,"") -> 0.35 | J75: 1 | K75: 1 | U75: mappa | V75: SHOWROOM | W75: Showroom | X75: =IFERROR(COUNTA(C75,G75,J75,L75,O75,P75,R75,S75,T75,U75)/10,"") -> 0.4 | Y75: =IF(AND(C75<>"",G75<>"",J75<>"",O75<>"",S75<>"",T75<>""),"SÍ","no") -> no | Z75: recorrido · marcado ESTÁ
A76: HC-LIB-016 | B76: Matt Mullican/ Rubbings | C76: Libros | D76: HC KBB | E76: Disponible | F76: 978-3-03764-461-4 | G76: 87000 | H76: 56550 | I76: =IFERROR((G76-H76)/G76,"") -> 0.35 | K76: 1 | U76: matt-mullican-rubbings | V76: Showroom | W76: Showroom | X76: =IFERROR(COUNTA(C76,G76,J76,L76,O76,P76,R76,S76,T76,U76)/10,"") -> 0.3 | Y76: =IF(AND(C76<>"",G76<>"",J76<>"",O76<>"",S76<>"",T76<>""),"SÍ","no") -> no | Z76: recorrido · marcado ESTÁ
A77: HC-LIB-017 | B77: Measuring the Universe | C77: Libros | D77: HC KBB | E77: Disponible | F77: HC/KBBMU | G77: 40000 | H77: 26000 | I77: =IFERROR((G77-H77)/G77,"") -> 0.35 | J77: 1 | K77: 1 | U77: measuring-the-universe | V77: SHOWROOM | W77: Showroom | X77: =IFERROR(COUNTA(C77,G77,J77,L77,O77,P77,R77,S77,T77,U77)/10,"") -> 0.4 | Y77: =IF(AND(C77<>"",G77<>"",J77<>"",O77<>"",S77<>"",T77<>""),"SÍ","no") -> no | Z77: recorrido · marcado ESTÁ
A78: HC-LIB-018 | B78: Mental Landscape | C78: Libros | D78: HC KBB | E78: Disponible | F78: 978-987-45783-3-4 | G78: 46000 | H78: 29900 | I78: =IFERROR((G78-H78)/G78,"") -> 0.35 | J78: 3 | K78: 3 | U78: mental-landscape | V78: 1 showroom, 2 placard | W78: Showroom + placard | X78: =IFERROR(COUNTA(C78,G78,J78,L78,O78,P78,R78,S78,T78,U78)/10,"") -> 0.4 | Y78: =IF(AND(C78<>"",G78<>"",J78<>"",O78<>"",S78<>"",T78<>""),"SÍ","no") -> no | Z78: recorrido · marcado ESTÁ
A79: HC-LIB-019 | B79: Miguel Rotschild | C79: Libros | D79: HC KBB | E79: Disponible | F79: 978-377-57402-4-1 | G79: 75000 | H79: 48750 | I79: =IFERROR((G79-H79)/G79,"") -> 0.35 | J79: 3 | K79: 3 | U79: miguel-rotschild | V79: Showroom/placard fondo | W79: Showroom + placard | X79: =IFERROR(COUNTA(C79,G79,J79,L79,O79,P79,R79,S79,T79,U79)/10,"") -> 0.4 | Y79: =IF(AND(C79<>"",G79<>"",J79<>"",O79<>"",S79<>"",T79<>""),"SÍ","no") -> no | Z79: recorrido · marcado ESTÁ
A80: HC-LIB-020 | B80: Music Stands Stills | C80: Libros | D80: HC KBB | E80: Disponible | F80: 978-907-567-9380 | G80: 52000 | H80: 33800 | I80: =IFERROR((G80-H80)/G80,"") -> 0.35 | K80: 3 | U80: music-stands-stills | V80: 1 showroom, 2 placard | W80: Showroom + placard | X80: =IFERROR(COUNTA(C80,G80,J80,L80,O80,P80,R80,S80,T80,U80)/10,"") -> 0.3 | Y80: =IF(AND(C80<>"",G80<>"",J80<>"",O80<>"",S80<>"",T80<>""),"SÍ","no") -> no | Z80: recorrido · alta resuelta contra el catálogo | AA80: visto como "Libro Jorge Macchi - Music stand still" · "Music Stands Stills", HC KBB
A81: HC-LIB-021 | B81: Nestlé Art Collection | C81: Libros | D81: HC KBB | E81: Disponible | F81: 978-3-03764-038-8 | G81: 100000 | H81: 65000 | I81: =IFERROR((G81-H81)/G81,"") -> 0.35 | J81: 1 | K81: 1 | U81: nestle-art-collection | V81: Showroom | W81: Showroom | X81: =IFERROR(COUNTA(C81,G81,J81,L81,O81,P81,R81,S81,T81,U81)/10,"") -> 0.4 | Y81: =IF(AND(C81<>"",G81<>"",J81<>"",O81<>"",S81<>"",T81<>""),"SÍ","no") -> no | Z81: recorrido · marcado ESTÁ
A82: HC-LIB-022 | B82: Not Made Visible | C82: Libros | D82: HC KBB | E82: Disponible | F82: HC/KBBNMV | G82: 52000 | H82: 33800 | I82: =IFERROR((G82-H82)/G82,"") -> 0.35 | J82: 1 | K82: 1 | U82: not-made-visible | V82: SHOWROOM | W82: Showroom | X82: =IFERROR(COUNTA(C82,G82,J82,L82,O82,P82,R82,S82,T82,U82)/10,"") -> 0.4 | Y82: =IF(AND(C82<>"",G82<>"",J82<>"",O82<>"",S82<>"",T82<>""),"SÍ","no") -> no | Z82: recorrido · marcado ESTÁ
A83: HC-LIB-023 | B83: Of Bridges & Borders Vol I | C83: Libros | D83: HC KBB | E83: Disponible | F83: 978-3-03764-081-4 | G83: 74000 | H83: 48100 | I83: =IFERROR((G83-H83)/G83,"") -> 0.35 | J83: 2 | K83: 2 | U83: of-bridges-borders-vol-i | V83: 1 Showroom, 1 placard | W83: Showroom + placard | X83: =IFERROR(COUNTA(C83,G83,J83,L83,O83,P83,R83,S83,T83,U83)/10,"") -> 0.4 | Y83: =IF(AND(C83<>"",G83<>"",J83<>"",O83<>"",S83<>"",T83<>""),"SÍ","no") -> no | Z83: recorrido · marcado ESTÁ | AA83: precio 72*
A84: HC-LIB-024 | B84: Of Bridges & Borders Vol II | C84: Libros | D84: HC KBB | E84: Disponible | F84: 978-3-03764-263-4 | G84: 50000 | H84: 32500 | I84: =IFERROR((G84-H84)/G84,"") -> 0.35 | J84: 4 | K84: 4 | U84: of-bridges-borders-vol-ii | V84: 2 Showroom/ 1 placard fondo/ 1 fotos? | W84: Showroom + placard | X84: =IFERROR(COUNTA(C84,G84,J84,L84,O84,P84,R84,S84,T84,U84)/10,"") -> 0.4 | Y84: =IF(AND(C84<>"",G84<>"",J84<>"",O84<>"",S84<>"",T84<>""),"SÍ","no") -> no | Z84: recorrido · marcado ESTÁ
A85: HC-LIB-025 | B85: Parse | C85: Libros | D85: HC KBB | E85: Disponible | F85: 978-3-03764-117-0 | G85: 113000 | H85: 73450 | I85: =IFERROR((G85-H85)/G85,"") -> 0.35 | K85: 1 | U85: parse | V85: SHOWROOM | W85: Showroom | X85: =IFERROR(COUNTA(C85,G85,J85,L85,O85,P85,R85,S85,T85,U85)/10,"") -> 0.3 | Y85: =IF(AND(C85<>"",G85<>"",J85<>"",O85<>"",S85<>"",T85<>""),"SÍ","no") -> no | Z85: recorrido · marcado ESTÁ
A86: HC-LIB-026 | B86: Premonition | C86: Libros | D86: HC KBB | E86: Disponible | F86: 978-3-7356-0816-1 | G86: 74000 | H86: 48100 | I86: =IFERROR((G86-H86)/G86,"") -> 0.35 | J86: 2 | K86: 2 | U86: premonition | V86: placard/showroom | W86: Showroom + placard | X86: =IFERROR(COUNTA(C86,G86,J86,L86,O86,P86,R86,S86,T86,U86)/10,"") -> 0.4 | Y86: =IF(AND(C86<>"",G86<>"",J86<>"",O86<>"",S86<>"",T86<>""),"SÍ","no") -> no | Z86: recorrido · marcado ESTÁ
A87: HC-LIB-027 | B87: RETOUR | C87: Libros | D87: HC KBB | E87: Disponible | F87: HC/KBBRT | G87: 135000 | H87: 87750 | I87: =IFERROR((G87-H87)/G87,"") -> 0.35 | J87: 3 | K87: 3 | U87: retour | V87: 1 showroom, 2 placard | W87: Showroom + placard | X87: =IFERROR(COUNTA(C87,G87,J87,L87,O87,P87,R87,S87,T87,U87)/10,"") -> 0.4 | Y87: =IF(AND(C87<>"",G87<>"",J87<>"",O87<>"",S87<>"",T87<>""),"SÍ","no") -> no | Z87: recorrido · marcado ESTÁ
A88: HC-LIB-028 | B88: Ronan & erwan bouroullec | C88: Libros | D88: HC KBB | E88: Disponible | F88: 978-3-03764-150-7 | G88: 35000 | H88: 22750 | I88: =IFERROR((G88-H88)/G88,"") -> 0.35 | J88: 2 | K88: 2 | U88: ronan-erwan-bouroullec | V88: Showroom | W88: Showroom | X88: =IFERROR(COUNTA(C88,G88,J88,L88,O88,P88,R88,S88,T88,U88)/10,"") -> 0.4 | Y88: =IF(AND(C88<>"",G88<>"",J88<>"",O88<>"",S88<>"",T88<>""),"SÍ","no") -> no | Z88: recorrido · marcado ESTÁ
A89: HC-LIB-029 | B89: Switzerlart | C89: Libros | D89: HC KBB | E89: Disponible | F89: HC/KBBSW | G89: 21000 | H89: 13650 | I89: =IFERROR((G89-H89)/G89,"") -> 0.35 | J89: 1 | K89: 1 | U89: switzerlart | V89: placard | W89: Placard fondo | X89: =IFERROR(COUNTA(C89,G89,J89,L89,O89,P89,R89,S89,T89,U89)/10,"") -> 0.4 | Y89: =IF(AND(C89<>"",G89<>"",J89<>"",O89<>"",S89<>"",T89<>""),"SÍ","no") -> no | Z89: recorrido · marcado ESTÁ
A90: HC-LIB-030 | B90: Teresa Burga: Aleatory Structures | C90: Libros | D90: HC KBB | E90: Disponible | F90: HC/KBBTB | G90: 75000 | H90: 48750 | I90: =IFERROR((G90-H90)/G90,"") -> 0.35 | J90: 1 | K90: 1 | U90: teresa-burga-aleatory-structures | V90: SHOWROOM | W90: Showroom | X90: =IFERROR(COUNTA(C90,G90,J90,L90,O90,P90,R90,S90,T90,U90)/10,"") -> 0.4 | Y90: =IF(AND(C90<>"",G90<>"",J90<>"",O90<>"",S90<>"",T90<>""),"SÍ","no") -> no | Z90: recorrido · marcado ESTÁ
A91: HC-LIB-031 | B91: Transversal | C91: Libros | D91: HC KBB | E91: Disponible | F91: 978-9874-57836-5 | G91: 65000 | H91: 42250 | I91: =IFERROR((G91-H91)/G91,"") -> 0.35 | J91: 1 | K91: 1 | U91: transversal | V91: Showroom | W91: Showroom | X91: =IFERROR(COUNTA(C91,G91,J91,L91,O91,P91,R91,S91,T91,U91)/10,"") -> 0.4 | Y91: =IF(AND(C91<>"",G91<>"",J91<>"",O91<>"",S91<>"",T91<>""),"SÍ","no") -> no | Z91: recorrido · marcado ESTÁ
A92: HC-LIB-032 | B92: Tuit du monde | C92: Libros | D92: HC KBB | E92: Disponible | F92: 978-3-03778-000-8 | G92: 40000 | H92: 26000 | I92: =IFERROR((G92-H92)/G92,"") -> 0.35 | K92: 2 | U92: tuit-du-monde | V92: 1 estudio, 1 showroom | W92: Showroom | X92: =IFERROR(COUNTA(C92,G92,J92,L92,O92,P92,R92,S92,T92,U92)/10,"") -> 0.3 | Y92: =IF(AND(C92<>"",G92<>"",J92<>"",O92<>"",S92<>"",T92<>""),"SÍ","no") -> no | Z92: recorrido · alta resuelta contra el catálogo | AA92: visto como "Libro Toit du Monde - Lars Miller" · "Tuit du monde" es el mismo libro mal tipeado; Lars Muller es la editorial
A93: HC-LIB-033 | B93: Ugo Rondinone: New Horizon | C93: Libros | D93: HC KBB | E93: Disponible | F93: 978-3-03764-506-2 | G93: 77000 | H93: 50050 | I93: =IFERROR((G93-H93)/G93,"") -> 0.35 | J93: 3 | K93: 3 | U93: ugo-rondinone-new-horizon | V93: showroom | W93: Showroom | X93: =IFERROR(COUNTA(C93,G93,J93,L93,O93,P93,R93,S93,T93,U93)/10,"") -> 0.4 | Y93: =IF(AND(C93<>"",G93<>"",J93<>"",O93<>"",S93<>"",T93<>""),"SÍ","no") -> no | Z93: recorrido · marcado ESTÁ
A94: HC-LIB-034 | B94: Ugo Rondinone: Pure sunshine | C94: Libros | D94: HC KBB | E94: Disponible | F94: 978-3-03764-505-5 | G94: 93000 | H94: 60450 | I94: =IFERROR((G94-H94)/G94,"") -> 0.35 | J94: 1 | K94: 1 | U94: ugo-rondinone-pure-sunshine | W94: Sin ubicación declarada | X94: =IFERROR(COUNTA(C94,G94,J94,L94,O94,P94,R94,S94,T94,U94)/10,"") -> 0.4 | Y94: =IF(AND(C94<>"",G94<>"",J94<>"",O94<>"",S94<>"",T94<>""),"SÍ","no") -> no | Z94: recorrido · marcado ESTÁ
A95: HC-LIB-035 | B95: Unreachable Empires | C95: Libros | D95: HC KBB | E95: Disponible | F95: 978-3-03764-514-7 | G95: 65000 | H95: 42250 | I95: =IFERROR((G95-H95)/G95,"") -> 0.35 | J95: 3 | K95: 3 | U95: unreachable-empires | V95: 2 Showroom 1 placard fondo | W95: Showroom + placard | X95: =IFERROR(COUNTA(C95,G95,J95,L95,O95,P95,R95,S95,T95,U95)/10,"") -> 0.4 | Y95: =IF(AND(C95<>"",G95<>"",J95<>"",O95<>"",S95<>"",T95<>""),"SÍ","no") -> no | Z95: recorrido · marcado ESTÁ
A96: HC-LIB-036 | B96: mika tanila | C96: Libros | D96: HC KBB | E96: Disponible | G96: 35000 | I96: =IFERROR((G96-H96)/G96,"") -> 1 | J96: 1 | U96: mika-tanila | X96: =IFERROR(COUNTA(C96,G96,J96,L96,O96,P96,R96,S96,T96,U96)/10,"") -> 0.4 | Y96: =IF(AND(C96<>"",G96<>"",J96<>"",O96<>"",S96<>"",T96<>""),"SÍ","no") -> no | Z96: NUEVO · no estaba en el inventario | AA96: El SKU de 35.000 (I081 Bouroullec) ya estaba marcado aparte: es un libro distinto
A97: HC-MUE-001 | B97: BANCO NEGRO 155x55x50h | C97: Muebles | D97: RUFFO | E97: Disponible (consignación) | F97: HC/RF04 | G97: 3146000 | H97: 2000000 | I97: =IFERROR((G97-H97)/G97,"") -> 0.36427209 | J97: 1 | K97: 1 | L97: 50 | M97: 155 | N97: 55 | U97: banco-negro-155x55x50h | V97: showroom | W97: Showroom | X97: =IFERROR(COUNTA(C97,G97,J97,L97,O97,P97,R97,S97,T97,U97)/10,"") -> 0.5 | Y97: =IF(AND(C97<>"",G97<>"",J97<>"",O97<>"",S97<>"",T97<>""),"SÍ","no") -> no | Z97: recorrido · marcado ESTÁ
A98: HC-MUE-002 | B98: BANCO TOTEM | C98: Muebles | D98: TALLER POSIBLE | E98: Disponible (consignación) | F98: HC/COCO02 | G98: 742456 | H98: 472000 | I98: =IFERROR((G98-H98)/G98,"") -> 0.36427209 | K98: 1 | U98: banco-totem | V98: showroom | W98: Showroom | X98: =IFERROR(COUNTA(C98,G98,J98,L98,O98,P98,R98,S98,T98,U98)/10,"") -> 0.3 | Y98: =IF(AND(C98<>"",G98<>"",J98<>"",O98<>"",S98<>"",T98<>""),"SÍ","no") -> no | Z98: recorrido · marcado ESTÁ
A99: HC-MUE-003 | B99: BANQUETA REGULABLE NEGRO | C99: Muebles | D99: SANTIAGO DEL CAMPO | E99: Disponible (consignación) | F99: HC/SCBR | G99: 944 | H99: 600 | I99: =IFERROR((G99-H99)/G99,"") -> 0.36440678 | K99: 2 | U99: banqueta-regulable-negro | V99: SHOWROOM | W99: Showroom | X99: =IFERROR(COUNTA(C99,G99,J99,L99,O99,P99,R99,S99,T99,U99)/10,"") -> 0.3 | Y99: =IF(AND(C99<>"",G99<>"",J99<>"",O99<>"",S99<>"",T99<>""),"SÍ","no") -> no | Z99: recorrido · marcado ESTÁ
A100: HC-MUE-004 | B100: BANQUETAS ROJAS LAQUEADAS Charles & Ray Eames | C100: Muebles | D100: SANTIAGO DEL CAMPO | E100: Disponible (consignación) | F100: HC/SCBR | G100: 1888 | H100: 1200 | I100: =IFERROR((G100-H100)/G100,"") -> 0.36440678 | J100: 2 | K100: 2 | U100: banquetas-rojas-laqueadas-charles-ray-eames | V100: SHOWROOM | W100: Showroom | X100: =IFERROR(COUNTA(C100,G100,J100,L100,O100,P100,R100,S100,T100,U100)/10,"") -> 0.4 | Y100: =IF(AND(C100<>"",G100<>"",J100<>"",O100<>"",S100<>"",T100<>""),"SÍ","no") -> no | Z100: recorrido · marcado ESTÁ | AA100: precio + iva
A101: HC-MUE-005 | B101: Banqueta Bar | C101: Muebles | E101: Disponible | G101: 346000 | I101: =IFERROR((G101-H101)/G101,"") -> 1 | J101: 1 | U101: banqueta-bar | X101: =IFERROR(COUNTA(C101,G101,J101,L101,O101,P101,R101,S101,T101,U101)/10,"") -> 0.4 | Y101: =IF(AND(C101<>"",G101<>"",J101<>"",O101<>"",S101<>"",T101<>""),"SÍ","no") -> no | Z101: NUEVO · no estaba en el inventario | AA101: Sin coincidencia de precio en el catálogo
...

Sheet Qué falta por campo
A1: Qué falta para que estos 149 se puedan publicar
A2: Ordenado por cuántos productos bloquea. Los primeros cinco bloquean los 149 por igual: son cinco tareas, no 149 problemas.
A4: Campo | B4: Completos | C4: Faltan | D4: Bloquea publicar | E4: Quién lo resuelve | F4: Cómo
A5: Peso kg | B5: =COUNTA('Inventario final'!O5:O153) -> 0 | C5: =149-B5 -> 149 | D5: SÍ | E5: Las socias / los proveedores | F5: Es el dato que bloquea el checkout: sin peso Tiendanube no cotiza envío. Se completa por proveedor, no de a uno.
A6: Foto | B6: =COUNTA('Inventario final'!T5:T153) -> 0 | C6: =149-B6 -> 149 | D6: SÍ | E6: Habitante Studio | F6: Pedir la carpeta HC HOME de Dropbox copiada a Drive. Convención de nombres: SKU-1.jpg.
A7: Descripción de venta | B7: =COUNTA('Inventario final'!S5:S153) -> 0 | C7: =149-B7 -> 149 | D7: SÍ | E7: Nosotros | F7: Con el documento de voz y textos ya cerrado. 149 textos cortos, se puede hacer por lote y categoría.
A8: Lead time días | B8: =COUNTA('Inventario final'!P5:P153) -> 0 | C8: =149-B8 -> 149 | D8: no | E8: Los proveedores | F8: Atributo del proveedor. 28 proveedores, 5 cubren 88 de los 149.
A9: Materiales | B9: =COUNTA('Inventario final'!R5:R153) -> 0 | C9: =149-B9 -> 149 | D9: no | E9: Las socias | F9: Necesario para la ficha, no para publicar.
A10: Reponible | B10: =COUNTA('Inventario final'!Q5:Q153) -> 0 | C10: =149-B10 -> 149 | D10: no | E10: Las socias | F10: Define si el stock va vacío (infinito) o con número en Tiendanube.
A11: Medidas | B11: =COUNTA('Inventario final'!M5:M153) -> 32 | C11: =149-B11 -> 117 | D11: no | E11: Medir en el local | F11: 117 sin medidas. Alto/ancho/prof van en columnas separadas para Tiendanube.
A12: Stock real contado | B12: =COUNTA('Inventario final'!J5:J153) -> 72 | C12: =149-B12 -> 77 | D12: SÍ | E12: El recorrido | F12: Esta pasada registró presencia, no cantidad. Decisión del 24/9: primero saber qué está.
A13: Categoría | B13: =COUNTA('Inventario final'!C5:C153) -> 124 | C13: =149-B13 -> 25 | D13: SÍ | E13: Las socias | F13: 25 sin categoría, con sugerencia en su propia hoja.
A14: Precio | B14: =COUNTA('Inventario final'!G5:G153) -> 148 | C14: =149-B14 -> 1 | D14: SÍ | E14: Las socias | F14: Sólo 1 producto sin precio.
A16: Productos listos para publicar hoy | B16: =COUNTIF('Inventario final'!Y5:Y153,"SÍ") -> 0
A17: Completitud promedio | B17: =AVERAGE('Inventario final'!X5:X153) -> 0.35234899
A19: Valor de lista del inventario verificado (1 unidad por SKU) | B19: =SUM('Inventario final'!G5:G153) -> 58375365
A20: Es valor de lista, no de stock: la cantidad real todavía no se contó.

Sheet Completar por proveedor
A1: Peso y lead time se completan acá, no producto por producto
A2: Principio acordado en la primera reunión: lead time, capacidad y reposición son atributos del proveedor. 28 proveedores cubren los 149 productos.
A4: Proveedor | B4: Productos | C4: % del inventario | D4: Régimen que usa | E4: Lead time días | F4: Reponible | G4: Contacto | H4: Peso: cómo lo informan
A5: HC KBB | B5: 36 | C5: =B5/149 -> 0.24161074 | D5: Disponible
A6: HC SOFI SUAYA | B6: 18 | C6: =B6/149 -> 0.12080537 | D6: Disponible
A7: HC AIRES DEL SUR | B7: 17 | C7: =B7/149 -> 0.11409396 | D7: Disponible
A8: FERMOB | B8: 10 | C8: =B8/149 -> 0.067114094 | D8: Disponible (consignación)
A9: HC | B9: 7 | C9: =B9/149 -> 0.046979866 | D9: Disponible
A10: HC PAIS TEXTIL PERU | B10: 7 | C10: =B10/149 -> 0.046979866 | D10: Disponible
A11: HC DUKAAN | B11: 6 | C11: =B11/149 -> 0.040268456 | D11: Disponible
A12: LIMO MARMOL | B12: 6 | C12: =B12/149 -> 0.040268456 | D12: Disponible · Disponible (consignación)
A13: HC HUS COMPRADO | B13: 4 | C13: =B13/149 -> 0.026845638 | D13: Disponible
A14: HC MISHKA | B14: 3 | C14: =B14/149 -> 0.020134228 | D14: Disponible
A15: HC JESUS NUDOS | B15: 3 | C15: =B15/149 -> 0.020134228 | D15: Disponible
A16: CSALOM ATELIER | B16: 3 | C16: =B16/149 -> 0.020134228 | D16: Disponible
... A32: SIXTA | B32: 1 | C32: =B32/149 -> 0.0067114094 | D32: Disponible (consignación)
A34: Suma de control | B34: =SUM(B5:B32) -> 149 | D34: Tiene que dar 149

Sheet Sin categoría
A1: 25 productos sin categoría
A2: La columna "Mi sugerencia" es inferencia mía a partir del nombre y el proveedor, no un dato. Aceptar o cambiar en la columna amarilla.
A4: SKU | B4: Nombre | C4: Proveedor | D4: Precio | E4: Mi sugerencia | F4: Categoría definitiva
A5: HC-GEN-001 | B5: AKAI LARGO | C5: TALLER POSIBLE | D5: 968968 | E5: Muebles
A6: HC-GEN-002 | B6: BACKGAMMON | C6: HC SOFI SUAYA | D6: 1328580 | E6: Objetos y deco
A7: HC-GEN-003 | B7: Butaca Umbral | C7: HC | D7: 2983105 | E7: Muebles
A8: HC-GEN-004 | B8: CABALLITO | C8: FERMOB | D8: 650 | E8: Objetos y deco
A9: HC-GEN-005 | B9: CENICEROS | C9: HC | D9: 206668 | E9: Objetos y deco
A10: HC-GEN-006 | B10: Casitas acrilico - chicas | C10: FABIANA BARREDA | D10: 347000 | E10: Objetos y deco
A11: HC-GEN-007 | B11: Casitas acrilicos - grandes | C11: FABIANA BARREDA | D11: 629200 | E11: Objetos y deco
A12: HC-GEN-008 | B12: Cilindro largo (78x18diam) | C12: CSALOM ATELIER | D12: 845000 | E12: Muebles
A13: HC-GEN-009 | B13: Cilindro mediano (58x18diam) | C13: CSALOM ATELIER | D13: 715000 | E13: Muebles
A14: HC-GEN-010 | B14: Cojin Yana Camino blanco y negro 30X45 | C14: HC PAIS TEXTIL PERU | D14: 112 | E14: Textiles
A15: HC-GEN-011 | B15: Cojin Yana alpaca y algodón con flecos 50X50 | C15: HC PAIS TEXTIL PERU | D15: 139 | E15: Textiles
A16: HC-GEN-012 | B16: Cojin Yana block blanco y negro 30X45 | C16: HC PAIS TEXTIL PERU | D16: 112 | E16: Textiles
... A29: HC-GEN-025 | B29: libro Bordeu | C29: HC DIAZ ORTIZ | D29: 100000 | E29: Libros

Sheet Altas resueltas
A1: Objetos dados de alta como "nuevos" que ya estaban en el catálogo
A2: Nueve de los quince. El local y el catálogo usan nombres distintos para la misma cosa; el precio de la etiqueta es lo que permite emparejarlos.
A4: Como se lo vio en el local | B4: Etiqueta | C4: SKU del catálogo | D4: Nombre en el catálogo | E4: Por qué es el mismo
A5: banco pelota | B5: precio 1967000 | C5: I181 | D5: RUFFO PELOTA | E5: precio 1.967.000 vs 1.966.250
A6: mesa ola mop | B6: 1926000 + iva | C6: I722 | D6: Mesa OLA modificada (100x60x45h) | E6: 1.926.000 + IVA = 2.330.460 vs 2.329.444
A7: Cuadro 1 - Santiago del Campo | B7: USD 2000 | C7: I182 | D7: Cuadros Chicos 35x45 | E7: USD 2000 x 1535 = 3.070.000, exacto. El proveedor es SANTIAGO CARRERA, no DEL CAMPO
A8: Cuadro 2 - Santiago del Campo | B8: 2000 usd | C8: I182 | D8: Cuadros Chicos 35x45 | E8: segunda unidad del mismo SKU (stock declarado 2)
A9: Libro - El romance vestido - Agustina Bothlink | C9: I408 | D9: Romance del vestido. | E9: "Romance del vestido.", HC DIAZ ORTIZ
A10: mesa arrime - madera negra | B10: 1342 usd | C10: I087 | D10: MESA DE APOYO (MADERA ROBLE NEGRO) | E10: precio 1342 exacto; confirma que 1342 era USD
A11: Libro Toit du Monde - Lars Miller | B11: sin etiquetar | C11: I085 | D11: Tuit du monde | E11: "Tuit du monde" es el mismo libro mal tipeado; Lars Muller es la editorial
A12: Libro Jorge Macchi - Music stand still | C12: I224 | D12: Music Stands Stills | E12: "Music Stands Stills", HC KBB
A13: Libro Enlargue - Diego Bianchi | B13: etiqueta: - | C13: I219 | D13: Enlarge | E13: "Enlarge"; ese SKU ya estaba marcado ESTÁ, asi que esta alta es redundante
A15: Cinco de los quince sí eran nuevos y están en el inventario con el origen "NUEVO".
A16: Uno quedó dudoso y está en la hoja "A confirmar".

Sheet Backlog
A1: Declarados por el inventario y no encontrados en el local
A2: No se descartan: quedan guardados. Hay que decidir si se reponen, si se buscan de nuevo o si se dan de baja.
A4: SKU viejo | B4: Nombre | C4: Proveedor | D4: Precio | E4: Stock declarado | F4: Ubicación declarada | G4: Qué hacer
A5: I023 | B5: SILLON UMBRAL CUERO PELO MARRON CLARO - 1 ESTRUCTURA CLARA, 1 ESTRUCTURA NEGRA | C5: HC | D5: 3129544 | E5: 2 | F5: Showroom
A6: I024 | B6: SILLON UMBRAL CUERO PELO MARRON OSCURO TEXTURADO 1 ESTRUCTURA NEGRA | C6: HC | D6: 3129544 | E6: 1 | F6: Showroom
A7: I082 | B7: Switzerlarch: Bank and Bastion | C7: HC KBB | D7: 21000 | E7: 1 | F7: SHOWROOM
A8: I144 | B8: CANASTOS LIANA MEDIANO | C8: HC SOFI SUAYA | D8: 177144 | E8: 1 | F8: Showroom
A9: I734 | B9: Mesa mármol Rosa Portugal D35x45 | C9: LIMO MARMOL | D9: 976 | E9: 0

Sheet A confirmar
A1: Preguntas que necesitan una respuesta humana
A2: Ninguna de estas la puedo resolver mirando datos. Están ordenadas por lo que bloquean.
A4: # | B4: Qué | C4: Por qué importa | D4: A quién | E4: Respuesta
A5: 1 | B5: Peso de los productos, al menos un rango por proveedor | C5: Sin peso Tiendanube no cotiza envío. Es el único dato que impide cobrar. | D5: Socias / proveedores
A6: 2 | B6: La carpeta HC HOME de Dropbox copiada a Google Drive | C6: Sin fotos no hay página de producto. Es el segundo bloqueante. | D6: Habitante Studio
A7: 3 | B7: ¿"mesa saporo redonda 45x40" es la Mesa oval saporo L.120 (I640)? | C7: La L.80 (I415) ya está marcada aparte. Si no es ninguna, es un producto nuevo. | D7: Quien recorrió
A8: 4 | B8: La etiqueta de la mesa de mármol rosa decía 88000000 | C8: Es un precio imposible. ¿Son $880.000 o $8.800.000? La del catálogo (D35x45) fue a backlog y esta es otra medida. | D8: Socias
A9: 5 | B9: "mika tanila" a $35.000: ¿qué libro es? | C9: El libro de $35.000 del catálogo (Bouroullec) ya está marcado aparte, así que este es otro. | D9: Socias / HC KBB
A10: 6 | B10: Banqueta Bar a $346.000 y Lámpara Mesa LED a $129.000: ¿de quién son? | C10: Son productos nuevos sin proveedor. Sin proveedor no hay lead time ni régimen. | D10: Socias
A11: 7 | B11: Santiago Carrera y Santiago del Campo son dos proveedores distintos | C11: Los cuadros son de Carrera; los muebles, de Del Campo. Se confundieron en el recorrido y en el cruce de septiembre. | D11: Confirmar con socias
A12: 8 | B12: ¿Qué sets se venden juntos y qué piezas sueltas? | C12: Hay sets y piezas como productos separados. Agrupar variantes DESPUÉS de importar obliga a borrar productos y perder las URLs. | D12: Socias
A13: 9 | B13: Los 3 objetos que existen con stock declarado 0 | C13: Dos Frascos EGG y una manta: están en el local y el inventario decía que no. ¿Se venden? | D13: Socias
A14: 10 | B14: El SILLON UMBRAL CUERO VACA: el inventario declara 2 y se contó 1 | C14: Es la única discrepancia real de cantidad de todo el recorrido. | D14: Quien recorrió
